datalake/__init__.py
datalake/annotation.py
datalake/constants.py
datalake/datalakeinterface.py
datalake/dataset.py
datalake/keys.py
datalake/label.py
datalake/logger.py
datalake/model.py
lx_dl_v1-0.0.1.dist-info/METADATA
lx_dl_v1-0.0.1.dist-info/WHEEL
lx_dl_v1-0.0.1.dist-info/top_level.txt
lx_dl_v1-0.0.1.dist-info/RECORD
